api/__init__.py
api/asgi.py
api/celery.py
api/settings.py
api/test_runner.py
api/urls.py
api/wsgi.py
api/analyst/__init__.py
api/analyst/admin.py
api/analyst/apps.py
api/analyst/forms.py
api/analyst/models.py
api/analyst/query_generator.py
api/analyst/serializers.py
api/analyst/tests.py
api/analyst/urls.py
api/analyst/views.py
api/analyst/migrations/0001_initial.py
api/analyst/migrations/0002_rename_dataentry_databasecred.py
api/analyst/migrations/0003_dataentry.py
api/analyst/migrations/__init__.py
api/audittrails/__init__.py
api/audittrails/admin.py
api/audittrails/apps.py
api/audittrails/serializers.py
api/audittrails/tests.py
api/audittrails/urls.py
api/audittrails/views.py
api/authentication/__init__.py
api/authentication/admin.py
api/authentication/apps.py
api/authentication/managers.py
api/authentication/models.py
api/authentication/serializers.py
api/authentication/tests.py
api/authentication/urls.py
api/authentication/views.py
api/authentication/migrations/0001_initial.py
api/authentication/migrations/__init__.py
api/dialogflow/__init__.py
api/dialogflow/admin.py
api/dialogflow/apps.py
api/dialogflow/middleware.py
api/dialogflow/models.py
api/dialogflow/prompt.py
api/dialogflow/serializers.py
api/dialogflow/signals.py
api/dialogflow/tests.py
api/dialogflow/urls.py
api/dialogflow/views.py
api/dialogflow/helpers/__init__.py
api/dialogflow/helpers/conversations.py
api/dialogflow/helpers/get_prompt_responses.py
api/dialogflow/helpers/intents.py
api/dialogflow/helpers/notify_click_up.py
api/dialogflow/helpers/problems_solutions.py
api/dialogflow/migrations/0001_initial.py
api/dialogflow/migrations/__init__.py
api/facebook/__init__.py
api/facebook/admin.py
api/facebook/apps.py
api/facebook/forms.py
api/facebook/models.py
api/facebook/prompts.py
api/facebook/tasks.py
api/facebook/tests.py
api/facebook/urls.py
api/facebook/views.py
api/facebook/migrations/0001_initial.py
api/facebook/migrations/__init__.py
api/gmail/__init__.py
api/gmail/admin.py
api/gmail/apps.py
lunyamwi-1.0.21.dist-info/METADATA
lunyamwi-1.0.21.dist-info/WHEEL
lunyamwi-1.0.21.dist-info/top_level.txt
lunyamwi-1.0.21.dist-info/RECORD
