Metadata-Version: 2.4
Name: lunyamwi
Version: 1.0.21
Summary: Lunyamwi is a social media management and automation tool.
Home-page: https://github.com/lunyamwis/boostedchat-scrapper-dev.git
Author: Martin Luther Bironga
Classifier: Programming Language :: Python :: 3
Classifier: License :: OSI Approved :: MIT License
Classifier: Operating System :: OS Independent
Requires-Python: >=3.6
Requires-Dist: requests
Dynamic: author
Dynamic: classifier
Dynamic: description
Dynamic: description-content-type
Dynamic: home-page
Dynamic: requires-dist
Dynamic: requires-python
Dynamic: summary
